[{"id": 1, "name": "triangle", "region": {"origin": {"x": 168, "y": 184}, "size": {"width": 63, "height": 38}}}, {"id": 2, "name": "square", "region": {"origin": {"x": 114.2919579377529, "y": 111.7919579377529}, "size": {"width": 59.416084124494205, "height": 59.416084124494205}}}, {"id": 3, "name": "circle", "region": {"origin": {"x": 34.5, "y": 174.0}, "size": {"width": 60.0, "height": 60.0}}}, {"id": 4, "name": "square", "region": {"origin": {"x": 54.21410248768545, "y": 129.21410248768547}, "size": {"width": 43.5717950246291, "height": 43.57179502462907}}}, {"id": 5, "name": "triangle", "region": {"origin": {"x": 164, "y": 16}, "size": {"width": 50, "height": 38}}}]