[{"id": 1, "name": "hexagon", "region": {"origin": {"x": 202.03653924610262, "y": 227.5180893055125}, "size": {"width": 29.92692150779476, "height": 26.96382138897502}}}, {"id": 2, "name": "rhombus", "region": {"origin": {"x": 153.0608987435044, "y": 63.05602684402404}, "size": {"width": 49.87820251299121, "height": 45.887946311951914}}}, {"id": 3, "name": "hexagon", "region": {"origin": {"x": 83.08282229116597, "y": 138.94100242582832}, "size": {"width": 67.83435541766806, "height": 61.11799514834337}}}, {"id": 4, "name": "rhombus", "region": {"origin": {"x": 117.54141114558298, "y": 218.041411145583}, "size": {"width": 33.91717770883402, "height": 33.917177708834004}}}, {"id": 5, "name": "triangle", "region": {"origin": {"x": 209, "y": 80}, "size": {"width": 39, "height": 106}}}]